exa/_C.so
exa/__init__.py
exa/__main__.py
exa/build_status
exa/common_pb/common_pb2.py
exa/compressors_pb/compressors_pb2.py
exa/exa_py
exa/module_repository_pb/module_repository_pb2.py
exa/module_repository_pb/module_repository_pb2_grpc.py
exa/py_client/default_session.py
exa/py_client/module.py
exa/py_client/profiler.py
exa/py_client/session.py
exa/py_docker/docker_templates.py
exa/py_docker/docker_tool.py
exa/py_docker/docker_wrappers.py
exa/py_local_e2e/default_config.pbtxt
exa/py_local_e2e/local_e2e_tool.py
exa/py_module/base_module.py
exa/py_module/base_module_context.py
exa/py_module/method_context.py
exa/py_module_repository/default_module_repository.py
exa/py_module_repository/module_repository.py
exa/py_module_repository/module_repository_images.py
exa/py_module_repository/module_repository_stub.py
exa/py_module_repository/module_repository_tool.py
exa/py_utils/argparse_utils.py
exa/py_value/value.py
exa/repo/__init__.py
exa/session_pb/session_pb2.py
exa/types.py
exafunction-0.16.0.dist-info/METADATA
exafunction-0.16.0.dist-info/RECORD
exafunction-0.16.0.dist-info/WHEEL
