Metadata-Version: 2.1
Name: exafunction
Version: 0.16.0
Author: Exafunction, Inc.
Author-email: douglas@exafunction.com
Requires-Dist: dill
Requires-Dist: docker
Requires-Dist: grpcio
Requires-Dist: numpy
Requires-Dist: protobuf < 4.0
Requires-Dist: requests
Requires-Dist: typing-extensions >= 4.1.0
